okik/__init__.py
okik/consts.py
okik/endpoints.py
okik/logger.py
okik/main.py
okik/scripts/__init__.py
okik/scripts/dockerfiles/__init__.py
okik/scripts/dockerfiles/dockerfile_gen.py
okik/utils/__init__.py
okik/utils/configs/__init__.py
okik/utils/configs/machines.py
okik/utils/configs/serviceconfigs.py
okik/utils/configs/yaml_configs.py
okik-0.0.342.dist-info/METADATA
okik-0.0.342.dist-info/WHEEL
okik-0.0.342.dist-info/entry_points.txt
okik-0.0.342.dist-info/RECORD
