Metadata-Version: 2.1
Name: okik
Version: 0.0.342
Summary: A Python package to serve python functions, classes, or .py files on a local server or cloud-based environment.
Home-page: https://www.okik.co.uk/
Author: Okik
Author-email: akash@okik.co.uk
Requires-Python: >=3.10,<4.0
Classifier: Programming Language :: Python :: 3
Classifier: Programming Language :: Python :: 3.10
Classifier: Programming Language :: Python :: 3.11
Classifier: Programming Language :: Python :: 3.12
Requires-Dist: Jinja2
Requires-Dist: MarkupSafe
Requires-Dist: PyYAML
Requires-Dist: Pygments
Requires-Dist: annotated-types
Requires-Dist: anyio
Requires-Dist: art
Requires-Dist: click
Requires-Dist: fastapi
Requires-Dist: filelock
Requires-Dist: fsspec
Requires-Dist: httpie
Requires-Dist: idna
Requires-Dist: kubernetes
Requires-Dist: markdown-it-py
Requires-Dist: mdurl
Requires-Dist: mpmath
Requires-Dist: networkx
Requires-Dist: numpy
Requires-Dist: pydantic (>=2.0.0)
Requires-Dist: pydantic_core
Requires-Dist: pyfiglet
Requires-Dist: questionary (>=2.0.1,<3.0.0)
Requires-Dist: rich
Requires-Dist: shellingham
Requires-Dist: sniffio
Requires-Dist: starlette
Requires-Dist: sympy
Requires-Dist: torch
Requires-Dist: typer
Requires-Dist: typing_extensions
